setup.cfg
setup.py
parse_cmake/__init__.py
parse_cmake/cmake_pprint.py
parse_cmake/list_utils.py
parse_cmake/parsing.py
parse_cmake/rand.py
parse_cmake.egg-info/PKG-INFO
parse_cmake.egg-info/SOURCES.txt
parse_cmake.egg-info/dependency_links.txt
parse_cmake.egg-info/entry_points.txt
parse_cmake.egg-info/not-zip-safe
parse_cmake.egg-info/requires.txt
parse_cmake.egg-info/top_level.txt
tests/__init__.py
tests/test_code_format.py
tests/test_example_inputs.py
tests/test_parsing.py