Metadata-Version: 1.1
Name: parse-cmake
Version: 0.4.1
Summary: Parser for CMakeLists.txt files
Home-page: http://github.com/wjwwood/parse_cmake
Author: Issac Trotts, William Woodall
Author-email: itrotts@willowgarage.com, william@osrfoundation.org
License: Apache 2.0
Platform: UNKNOWN
Classifier: Environment :: Console
Classifier: Intended Audience :: Developers
Classifier: License :: OSI Approved :: Apache Software License
Classifier: Programming Language :: Python
